common/__init__.py
common/app/__init__.py
common/app/app_base.py
common/app/app_entrypoint.py
common/app/app_terminate.py
common/app/health_check.py
common/app/signals.py
common/app/tests/__init__.py
common/app/tests/exceptions.py
common/app/tests/test_app.py
common/app/tests/test_health_check.py
common/config/__init__.py
common/config/config.py
common/config/tests/__init__.py
common/config/tests/test_config.py
common/examples/__init__.py
common/examples/asyncq/__init__.py
common/examples/asyncq/application.py
common/examples/asyncq/config.py
common/examples/asyncq/main.py
common/logger/__init__.py
common/logger/logger.py
py_12f_common-0.8.0.dist-info/LICENSE
py_12f_common-0.8.0.dist-info/METADATA
py_12f_common-0.8.0.dist-info/WHEEL
py_12f_common-0.8.0.dist-info/top_level.txt
py_12f_common-0.8.0.dist-info/RECORD
