Metadata-Version: 2.1
Name: py-12f-common
Version: 0.8.0
Summary: This repository holds those infrastructure-level modules, that every application requires that follows the core 12-factor principles.
Home-page: https://github.com/tombenke/py-12f-common
Author: Tamás Benke
Author-email: tombenke@gmail.com
License: MIT
Classifier: Programming Language :: Python
Classifier: Programming Language :: Python :: 3
Classifier: Programming Language :: Python :: 3.8
Requires-Python: >=3.8
License-File: LICENSE
Requires-Dist: argparse
Requires-Dist: dataclasses
Requires-Dist: python-dotenv
Requires-Dist: loguru
Requires-Dist: aiohttp
Requires-Dist: requests
Provides-Extra: dev
Requires-Dist: build ; extra == 'dev'
Requires-Dist: coverage ; extra == 'dev'
Requires-Dist: coverage-badge ; extra == 'dev'
Requires-Dist: black ; extra == 'dev'
Requires-Dist: pydeps ; extra == 'dev'
Requires-Dist: pylint ; extra == 'dev'
Requires-Dist: sphinx (>=4.4.0) ; extra == 'dev'
Requires-Dist: sphinx-rtd-theme ; extra == 'dev'
Requires-Dist: twine ; extra == 'dev'
